asynchronous_utils/__init__.py
asynchronous_utils-0.1.0.dist-info/licenses/LICENSE
asynchronous_utils-0.1.0.dist-info/METADATA
asynchronous_utils-0.1.0.dist-info/WHEEL
asynchronous_utils-0.1.0.dist-info/top_level.txt
asynchronous_utils-0.1.0.dist-info/RECORD
