Metadata-Version: 2.4
Name: asynchronous-utils
Version: 0.1.0
Summary: Python Async Utils
Author-email: Fabio Antonio Astore <astore.a.fabio@gmail.com>
License: MIT License
License-File: LICENSE
Dynamic: license-file
